{
  "identifier": "default",
  "description": "Default permissions for the bot.",
  "local": true,
  "windows": [
    "main"
  ],
  "platforms": [
    "macOS",
    "windows"
  ],
  "permissions": [
    "core:default",
    "fs:allow-read-file",
    "fs:allow-write-file",
    "fs:allow-read-dir",
    "fs:allow-mkdir",
    "fs:allow-exists",
    {
      "identifier": "fs:scope",
      "allow": [
        "$APP/*"
      ]
    },
    "shell:allow-open",
    "fs:default",
    "shell:default",
    "updater:default"
  ]
}